featuretools_tsfresh_primitives/__init__.py
featuretools_tsfresh_primitives/utils.py
featuretools_tsfresh_primitives/primitives/__init__.py
featuretools_tsfresh_primitives/primitives/abs_energy.py
featuretools_tsfresh_primitives/primitives/absolute_sum_of_changes.py
featuretools_tsfresh_primitives/primitives/agg_autocorrelation.py
featuretools_tsfresh_primitives/primitives/agg_linear_trend.py
featuretools_tsfresh_primitives/primitives/approximate_entropy.py
featuretools_tsfresh_primitives/primitives/ar_coefficient.py
featuretools_tsfresh_primitives/primitives/augmented_dickey_fuller.py
featuretools_tsfresh_primitives/primitives/autocorrelation.py
featuretools_tsfresh_primitives/primitives/binned_entropy.py
featuretools_tsfresh_primitives/primitives/c3.py
featuretools_tsfresh_primitives/primitives/change_quantiles.py
featuretools_tsfresh_primitives/primitives/cid_ce.py
featuretools_tsfresh_primitives/primitives/count_above.py
featuretools_tsfresh_primitives/primitives/count_above_mean.py
featuretools_tsfresh_primitives/primitives/count_below.py
featuretools_tsfresh_primitives/primitives/count_below_mean.py
featuretools_tsfresh_primitives/primitives/cwt_coefficients.py
featuretools_tsfresh_primitives/primitives/energy_ratio_by_chunks.py
featuretools_tsfresh_primitives/primitives/fft_aggregated.py
featuretools_tsfresh_primitives/primitives/fft_coefficient.py
featuretools_tsfresh_primitives/primitives/first_location_of_maximum.py
featuretools_tsfresh_primitives/primitives/first_location_of_minimum.py
featuretools_tsfresh_primitives/primitives/friedrich_coefficients.py
featuretools_tsfresh_primitives/primitives/has_duplicate.py
featuretools_tsfresh_primitives/primitives/has_duplicate_max.py
featuretools_tsfresh_primitives/primitives/has_duplicate_min.py
featuretools_tsfresh_primitives/primitives/index_mass_quantile.py
featuretools_tsfresh_primitives/primitives/kurtosis.py
featuretools_tsfresh_primitives/primitives/large_standard_deviation.py
featuretools_tsfresh_primitives-1.0.2.dist-info/LICENSE
featuretools_tsfresh_primitives-1.0.2.dist-info/METADATA
featuretools_tsfresh_primitives-1.0.2.dist-info/WHEEL
featuretools_tsfresh_primitives-1.0.2.dist-info/entry_points.txt
featuretools_tsfresh_primitives-1.0.2.dist-info/top_level.txt
featuretools_tsfresh_primitives-1.0.2.dist-info/RECORD
