Metadata-Version: 2.1
Name: featuretools-tsfresh-primitives
Version: 1.0.2
Summary: TSFresh primitives for featuretools
Home-page: https://github.com/alteryx/featuretools-tsfresh-primitives/
Author: Feature Labs, Inc.
Author-email: support@featurelabs.com
License: MIT
Platform: UNKNOWN
Classifier: Development Status :: 3 - Alpha
Classifier: Intended Audience :: Developers
Classifier: Programming Language :: Python :: 3
Classifier: Programming Language :: Python :: 3.7
Classifier: Programming Language :: Python :: 3.8
Classifier: Programming Language :: Python :: 3.9
Requires-Python: >=3.7, <4
License-File: LICENSE
Requires-Dist: tsfresh (>=0.19.0)
Requires-Dist: pandas (<2.0.0,>=1.3.0)
Requires-Dist: featuretools (>=1.0.0)
